notebookManagerPackageN/__init__.py
notebookManagerPackageN/notebook_manager.py
notebookManagerPackageNN-0.3.dist-info/METADATA
notebookManagerPackageNN-0.3.dist-info/WHEEL
notebookManagerPackageNN-0.3.dist-info/top_level.txt
notebookManagerPackageNN-0.3.dist-info/RECORD
